muskingumcunge/__init__.py
muskingumcunge/reach.py
muskingumcunge/timeseriestools.py
muskingumcunge-0.0.1.dist-info/LICENSE
muskingumcunge-0.0.1.dist-info/METADATA
muskingumcunge-0.0.1.dist-info/WHEEL
muskingumcunge-0.0.1.dist-info/top_level.txt
muskingumcunge-0.0.1.dist-info/RECORD
