Metadata-Version: 2.1
Name: muskingumcunge
Version: 0.0.1
Summary: Python implementation of the Muskingum-Cunge routing model.
Author-email: Scott Lawson <scott.lawson@uvm.edu>
License: MIT License
Project-URL: Homepage, https://github.com/sclaw/muskingum-cunge
Keywords: Channel Routing,muskingum,hydrology,hydrologic,model,channel,routing
Classifier: License :: OSI Approved :: MIT License
Classifier: Programming Language :: Python
Classifier: Programming Language :: Python :: 3
Requires-Python: >=3.9
License-File: LICENSE
Requires-Dist: numpy
